{
  "$schema": "https://schemas.wp.org/trunk/block.json",
  "apiVersion": 3,
  "name": "miscellaneous-gutenberg-blocks/flexbox",
  "version": "0.1.0",
  "title": "Flexbox",
  "category": "miscellaneous-gutenberg-blocks",
  "icon": "<svg width=\"24\" height=\"24\" xmlns=\"http://www.w3.org/2000/svg\" fill=\"none\" viewBox=\"0 0 24 24\" stroke-width=\"1.5\" stroke=\"currentColor\" ><path stroke-linecap=\"round\" stroke-linejoin=\"round\" d=\"M9 4.5v15m6-15v15m-10.875 0h15.75c.621 0 1.125-.504 1.125-1.125V5.625c0-.621-.504-1.125-1.125-1.125H4.125C3.504 4.5 3 5.004 3 5.625v12.75c0 .621.504 1.125 1.125 1.125Z\" /></svg>",
  "description": "Flexbox container",
  "example": {},
  "supports": {
    "color": {
      "background": true,
      "text": true
    },
    "typography": {
      "fontSize": true,
      "lineHeight": true,
      "textAlign": true
    },
    "background": {
      "backgroundImage": true,
      "backgroundSize": true
    },
    "shadow": true,
    "align": true,
    "alignWide": true,
    "spacing": {
      "margin": true,
      "padding": true
    }
  },
  "attributes": {
    "column": {
      "type": "number",
      "default": 0
    },
    "wrap": {
      "type": "boolean",
      "default": false
    },
    "tablet_wrap": {
      "type": "boolean",
      "default": false
    },
    "mobile_wrap": {
      "type": "boolean",
      "default": false
    },
    "horizontal": {
      "type": "boolean",
      "default": true
    },
    "tablet_horizontal": {
      "type": "boolean",
      "default": true
    },
    "mobile_horizontal": {
      "type": "boolean",
      "default": true
    },
    "reverse": {
      "type": "boolean",
      "default": false
    },
    "tablet_reverse": {
      "type": "boolean",
      "default": false
    },
    "mobile_reverse": {
      "type": "boolean",
      "default": false
    },
    "column_gap": {
      "type": "number",
      "default": 0
    },
    "tablet_column_gap": {
      "type": "number",
      "default": 0
    },
    "mobile_column_gap": {
      "type": "number",
      "default": 0
    },
    "column_gap_unit": {
      "type": "string",
      "default": "px"
    },
    "tablet_column_gap_unit": {
      "type": "string",
      "default": "px"
    },
    "mobile_column_gap_unit": {
      "type": "string",
      "default": "px"
    },
    "row_gap": {
      "type": "number",
      "default": 0
    },
    "tablet_row_gap": {
      "type": "number",
      "default": 0
    },
    "mobile_row_gap": {
      "type": "number",
      "default": 0
    },
    "row_gap_unit": {
      "type": "string",
      "default": "px"
    },
    "tablet_row_gap_unit": {
      "type": "string",
      "default": "px"
    },
    "mobile_row_gap_unit": {
      "type": "string",
      "default": "px"
    },
    "justify_content": {
      "type": "string",
      "default": "flex-start"
    },
    "tablet_justify_content": {
      "type": "string",
      "default": "flex-start"
    },
    "mobile_justify_content": {
      "type": "string",
      "default": "flex-start"
    },
    "align_items": {
      "type": "string",
      "default": "flex-start"
    },
    "tablet_align_items": {
      "type": "string",
      "default": "flex-start"
    },
    "mobile_align_items": {
      "type": "string",
      "default": "flex-start"
    },
    "width": {
      "type": "number",
      "default": 100
    },
    "tablet_width": {
      "type": "number",
      "default": 100
    },
    "mobile_width": {
      "type": "number",
      "default": 100
    },
    "grow": {
      "type": "boolean",
      "default": false
    },
    "tablet_grow": {
      "type": "boolean",
      "default": false
    },
    "mobile_grow": {
      "type": "boolean",
      "default": false
    },
    "shrink": {
      "type": "boolean",
      "default": false
    },
    "tablet_shrink": {
      "type": "boolean",
      "default": false
    },
    "mobile_shrink": {
      "type": "boolean",
      "default": false
    },
    "hidden": {
      "type": "boolean",
      "default": false
    },
    "tablet_hidden": {
      "type": "boolean",
      "default": false
    },
    "mobile_hidden": {
      "type": "boolean",
      "default": false
    }
  },
  "textdomain": "miscellaneous-gutenberg-blocks",
  "editorScript": "file:./index.js",
  "editorStyle": "file:./index.css",
  "style": "file:./style-index.css",
  "render": "file:./render.php"
}